krcg_bot/__init__.py
krcg_bot/__main__.py
krcg_bot-4.3.dist-info/LICENSE
krcg_bot-4.3.dist-info/METADATA
krcg_bot-4.3.dist-info/WHEEL
krcg_bot-4.3.dist-info/entry_points.txt
krcg_bot-4.3.dist-info/top_level.txt
krcg_bot-4.3.dist-info/zip-safe
krcg_bot-4.3.dist-info/RECORD
