Metadata-Version: 2.2
Name: krcg-bot
Version: 4.3
Summary: "Discord bot for VTES cards",
Home-page: http://github.com/lionel-panhaleux/krcg-bot
Author: lionelpx
Author-email: lionel.panhaleux@gmail.com
License: "MIT"
Keywords: vampire vtes ccg discord bot
Classifier: Development Status :: 5 - Production/Stable
Classifier: Intended Audience :: End Users/Desktop
Classifier: Natural Language :: English
Classifier: Operating System :: OS Independent
Classifier: Environment :: Plugins
Classifier: Programming Language :: Python :: 3
Classifier: Programming Language :: Python :: 3.9
Classifier: Topic :: Games/Entertainment
Requires-Python: >=3.8
License-File: LICENSE
Requires-Dist: hikari
Requires-Dist: krcg>=4.6
Requires-Dist: setuptools
Requires-Dist: unidecode
Provides-Extra: dev
Requires-Dist: black; extra == "dev"
Requires-Dist: doc8; extra == "dev"
Requires-Dist: flake8; extra == "dev"
Requires-Dist: ipython; extra == "dev"
Requires-Dist: pytest; extra == "dev"
Requires-Dist: zest.releaser[recommended]; extra == "dev"
